pointing/__init__.py
pointing-0.0.2.dist-info/LICENSE.txt
pointing-0.0.2.dist-info/METADATA
pointing-0.0.2.dist-info/WHEEL
pointing-0.0.2.dist-info/top_level.txt
pointing-0.0.2.dist-info/RECORD
