Metadata-Version: 2.1
Name: pointing
Version: 0.0.2
Summary: pointclasses for deltaclasses
Author-email: Johannes Programming <johannes-programming@posteo.org>
License: The MIT License (MIT)
Project-URL: download, https://pypi.org/project/pointing/#files
Project-URL: source, https://github.com/johannes-programming/pointing
Classifier: License :: OSI Approved :: MIT License
Classifier: Programming Language :: Python
Classifier: Programming Language :: Python :: 3
Requires-Python: >=3.11
License-File: LICENSE.txt
